lhereader/__init__.py
lhereader-1.0.11.dist-info/LICENSE
lhereader-1.0.11.dist-info/METADATA
lhereader-1.0.11.dist-info/WHEEL
lhereader-1.0.11.dist-info/top_level.txt
lhereader-1.0.11.dist-info/RECORD
