Metadata-Version: 2.1
Name: lhereader
Version: 1.0.11
Summary: A python module to read LHE files.
Home-page: https://github.com/AndreasAlbert/lhereader
Author: Andreas Albert
Author-email: andreas.albert@cern.ch
License: UNKNOWN
Keywords: lhe madgraph parser reader reading parsing
Platform: UNKNOWN
Requires-Dist: scikit-hep
